jsondir/__init__.py
jsondir/jsondir.py
jsondir-0.1.0.dist-info/LICENSE
jsondir-0.1.0.dist-info/METADATA
jsondir-0.1.0.dist-info/WHEEL
jsondir-0.1.0.dist-info/entry_points.txt
jsondir-0.1.0.dist-info/top_level.txt
jsondir-0.1.0.dist-info/RECORD
